luq89/__init__.py
luq89/pyspark/__init__.py
luq89/pyspark/spark_tools.py
luq89_pyspark_app_luq89-0.0.8.dist-info/LICENSE
luq89_pyspark_app_luq89-0.0.8.dist-info/METADATA
luq89_pyspark_app_luq89-0.0.8.dist-info/WHEEL
luq89_pyspark_app_luq89-0.0.8.dist-info/top_level.txt
luq89_pyspark_app_luq89-0.0.8.dist-info/RECORD
