Metadata-Version: 2.1
Name: luq89-pyspark-app-luq89
Version: 0.0.8
Summary: Sample app in PyPI
Home-page: https://github.com/lukaszziobro89
Author: Lukasz Ziobro
Author-email: luki670@wp.pl
License: UNKNOWN
Platform: UNKNOWN
Classifier: Programming Language :: Python :: 3
Classifier: License :: OSI Approved :: MIT License
Classifier: Operating System :: OS Independent
Requires-Python: >=3.6
Requires-Dist: bleach (==3.3.0)
Requires-Dist: build (==0.3.1.post1)
Requires-Dist: certifi (==2020.12.5)
Requires-Dist: cffi (==1.14.5)
Requires-Dist: chardet (==4.0.0)
Requires-Dist: colorama (==0.4.4)
Requires-Dist: cryptography (==3.4.7)
Requires-Dist: docutils (==0.17.1)
Requires-Dist: idna (==2.10)
Requires-Dist: importlib-metadata (==4.0.1)
Requires-Dist: jeepney (==0.6.0)
Requires-Dist: keyring (==23.0.1)
Requires-Dist: packaging (==20.9)
Requires-Dist: pep517 (==0.10.0)
Requires-Dist: pkginfo (==1.7.0)
Requires-Dist: py4j (==0.10.9)
Requires-Dist: pycparser (==2.20)
Requires-Dist: Pygments (==2.9.0)
Requires-Dist: pyparsing (==2.4.7)
Requires-Dist: pyspark (==3.1.1)
Requires-Dist: readme-renderer (==29.0)
Requires-Dist: requests (==2.25.1)
Requires-Dist: requests-toolbelt (==0.9.1)
Requires-Dist: rfc3986 (==1.4.0)
Requires-Dist: SecretStorage (==3.3.1)
Requires-Dist: six (==1.16.0)
Requires-Dist: toml (==0.10.2)
Requires-Dist: tqdm (==4.60.0)
Requires-Dist: twine (==3.4.1)
Requires-Dist: typing-extensions (==3.10.0.0)
Requires-Dist: urllib3 (==1.26.4)
Requires-Dist: webencodings (==0.5.1)
Requires-Dist: zipp (==3.4.1)
